desssign/__init__.py
desssign/__main__.py
desssign/common/__init__.py
desssign/common/design_check.py
desssign/common/enums.py
desssign/common/model.py
desssign/common/utils.py
desssign/concrete/__init__.py
desssign/concrete/concrete_material.py
desssign/concrete/concrete_member.py
desssign/concrete/concrete_section.py
desssign/concrete/constants.py
desssign/concrete/design_checks/design_check.py
desssign/concrete/design_checks/member_1d_checks.py
desssign/concrete/rebar_material.py
desssign/concrete/strength_classes.py
desssign/concrete/stress_strain_profile.py
desssign/loads/__init__.py
desssign/loads/enums.py
desssign/loads/load_case.py
desssign/loads/load_case_combination.py
desssign/loads/load_case_group.py
desssign/loads/load_combination_generator/__init__.py
desssign/loads/load_combination_generator/combination_generator.py
desssign/loads/load_combination_generator/constants.py
desssign/loads/load_combination_generator/generate_combinations.py
desssign/loads/snow/__init__.py
desssign/loads/snow/constants.py
desssign/loads/snow/enums.py
desssign/loads/snow/snow_load.py
desssign/loads/wind/__init__.py
desssign/loads/wind/constants.py
desssign/loads/wind/enums.py
desssign/loads/wind/external_pressure_coefficients.py
desssign/loads/wind/roofs.py
desssign/loads/wind/wind_load.py
desssign/py.typed
desssign/utils.py
desssign/wood/__init__.py
desssign/wood/constants.py
desssign/wood/design_checks/design_check.py
desssign/wood/design_checks/member_1d_checks.py
desssign/wood/enums.py
desssign/wood/strength_classes.py
desssign/wood/wood_material.py
desssign/wood/wood_member.py
desssign/wood/wood_section.py
desssign-0.0.14.dist-info/LICENSE
desssign-0.0.14.dist-info/METADATA
desssign-0.0.14.dist-info/WHEEL
desssign-0.0.14.dist-info/entry_points.txt
desssign-0.0.14.dist-info/RECORD
