Metadata-Version: 2.1
Name: desssign
Version: 0.0.14
Summary: desssign
Home-page: https://github.com/DanBeranek/desssign
License: MIT
Author: Daniel Beranek
Author-email: daniel.beraanek@gmail.com
Requires-Python: >=3.9,<4.0
Classifier: Development Status :: 2 - Pre-Alpha
Classifier: License :: OSI Approved :: MIT License
Classifier: Programming Language :: Python :: 3
Classifier: Programming Language :: Python :: 3.9
Classifier: Programming Language :: Python :: 3.10
Classifier: Programming Language :: Python :: 3.11
Classifier: Programming Language :: Python :: 3.12
Requires-Dist: aenum (>=3.1.15,<4.0.0)
Requires-Dist: click (>=8.0.1)
Requires-Dist: framesss (>=0.0.8,<1.0.1)
Requires-Dist: matplotlib (>=3.9.2,<4.0.0)
Requires-Dist: numpy (>=1.26.4,<2.0.0)
Project-URL: Changelog, https://github.com/DanBeranek/desssign/releases
Project-URL: Documentation, https://DanBeranek.github.io/desssign
Project-URL: Repository, https://github.com/DanBeranek/desssign
